qcrawl/__init__.py
qcrawl/cli.py
qcrawl/exporters.py
qcrawl/settings.py
qcrawl/signals.py
qcrawl/storage.py
qcrawl/core/__init__.py
qcrawl/core/_msgspec.py
qcrawl/core/crawler.py
qcrawl/core/engine.py
qcrawl/core/item.py
qcrawl/core/page.py
qcrawl/core/queue.py
qcrawl/core/request.py
qcrawl/core/response.py
qcrawl/core/scheduler.py
qcrawl/core/spider.py
qcrawl/core/stats.py
qcrawl/core/queues/__init__.py
qcrawl/core/queues/disk.py
qcrawl/core/queues/factory.py
qcrawl/core/queues/memory.py
qcrawl/core/queues/redis.py
qcrawl/downloaders/__init__.py
qcrawl/downloaders/base.py
qcrawl/downloaders/camoufox.py
qcrawl/downloaders/handler_manager.py
qcrawl/downloaders/http.py
qcrawl/middleware/__init__.py
qcrawl/middleware/base.py
qcrawl/middleware/manager.py
qcrawl/middleware/downloader/__init__.py
qcrawl/middleware/downloader/concurrency.py
qcrawl/middleware/downloader/cookies.py
qcrawl/middleware/downloader/download_delay.py
qcrawl/middleware/downloader/httpauth.py
qcrawl/middleware/downloader/httpcompression.py
qcrawl/middleware/downloader/httpproxy.py
qcrawl/middleware/downloader/redirect.py
qcrawl/middleware/downloader/retry.py
qcrawl/middleware/downloader/robotstxt.py
qcrawl/middleware/spider/__init__.py
qcrawl/middleware/spider/depth.py
qcrawl/middleware/spider/httperror.py
qcrawl/middleware/spider/offsite.py
qcrawl/pipelines/__init__.py
qcrawl/pipelines/base.py
qcrawl/pipelines/duplicate.py
qcrawl/pipelines/manager.py
qcrawl/pipelines/validation.py
qcrawl/runner/__init__.py
qcrawl/runner/engine.py
qcrawl/runner/export.py
qcrawl/runner/logging.py
qcrawl/runner/pipelines.py
qcrawl/runner/run.py
qcrawl/utils/__init__.py
qcrawl/utils/env.py
qcrawl/utils/fingerprint.py
qcrawl/utils/middleware.py
qcrawl/utils/settings.py
qcrawl/utils/url.py
qcrawl-0.3.5.dist-info/METADATA
qcrawl-0.3.5.dist-info/WHEEL
qcrawl-0.3.5.dist-info/entry_points.txt
qcrawl-0.3.5.dist-info/licenses/LICENSE
qcrawl-0.3.5.dist-info/RECORD
